dm_robotics/agentflow/__init__.py
dm_robotics/agentflow/action_spaces.py
dm_robotics/agentflow/action_spaces_test.py
dm_robotics/agentflow/composite_action_space_test.py
dm_robotics/agentflow/core.py
dm_robotics/agentflow/decorators.py
dm_robotics/agentflow/run_tests.py
dm_robotics/agentflow/spec_utils.py
dm_robotics/agentflow/spec_utils_test.py
dm_robotics/agentflow/subtask.py
dm_robotics/agentflow/subtask_test.py
dm_robotics/agentflow/testing_functions.py
dm_robotics/agentflow/testing_functions_test.py
dm_robotics/agentflow/util.py
dm_robotics/agentflow/loggers/print_logger.py
dm_robotics/agentflow/loggers/subtask_logger.py
dm_robotics/agentflow/loggers/subtask_logger_test.py
dm_robotics/agentflow/loggers/types.py
dm_robotics/agentflow/loggers/utils.py
dm_robotics/agentflow/loggers/utils_test.py
dm_robotics/agentflow/meta_options/control_flow/__init__.py
dm_robotics/agentflow/meta_options/control_flow/cond.py
dm_robotics/agentflow/meta_options/control_flow/cond_test.py
dm_robotics/agentflow/meta_options/control_flow/loop_ops.py
dm_robotics/agentflow/meta_options/control_flow/loop_ops_test.py
dm_robotics/agentflow/meta_options/control_flow/sequence.py
dm_robotics/agentflow/meta_options/control_flow/sequence_test.py
dm_robotics/agentflow/options/basic_options.py
dm_robotics/agentflow/options/basic_options_test.py
dm_robotics/agentflow/preprocessors/observation_transforms.py
dm_robotics/agentflow/preprocessors/observation_transforms_test.py
dm_robotics/agentflow/preprocessors/rewards.py
dm_robotics/agentflow/preprocessors/rewards_test.py
dm_robotics/agentflow/preprocessors/timestep_preprocessor.py
dm_robotics/agentflow/preprocessors/timestep_preprocessor_test.py
dm_robotics/agentflow/rendering/graphviz_renderer.py
dm_robotics/agentflow/rendering/graphviz_renderer_test.py
dm_robotics/agentflow/rendering/intermediate.py
dm_robotics/agentflow/rendering/intermediate_test.py
dm_robotics/agentflow/rendering/subgraph.py
dm_robotics/agentflow/rendering/subgraph_test.py
dm_robotics_agentflow-0.10.0.dist-info/licenses/LICENSE
dm_robotics_agentflow-0.10.0.dist-info/METADATA
dm_robotics_agentflow-0.10.0.dist-info/WHEEL
dm_robotics_agentflow-0.10.0.dist-info/top_level.txt
dm_robotics_agentflow-0.10.0.dist-info/zip-safe
dm_robotics_agentflow-0.10.0.dist-info/RECORD
