Metadata-Version: 2.4
Name: dm_robotics-agentflow
Version: 0.10.0
Summary: Tools for single-embodiment, multiple-task, Reinforcement Learning
Home-page: https://github.com/deepmind/dm_robotics/tree/main/py/agentflow
Author: DeepMind
License: Apache 2.0
Classifier: Development Status :: 5 - Production/Stable
Classifier: Programming Language :: Python :: 3
Classifier: License :: OSI Approved :: Apache Software License
Classifier: Operating System :: OS Independent
Classifier: Topic :: Software Development :: Libraries
Classifier: Topic :: Scientific/Engineering
Requires-Python: >=3.9, <3.13
License-File: LICENSE
Requires-Dist: dm_robotics-transformations
Requires-Dist: dm_robotics-geometry
Requires-Dist: numpy<3.0,>=2.0
Requires-Dist: dm_control==1.0.31
Requires-Dist: mujoco==3.3.3
Requires-Dist: opencv-python>=3.4.0
Requires-Dist: attrs>=20.3.0
Requires-Dist: pydot>=1.2.4
Requires-Dist: typing-extensions>=3.7.4
Dynamic: author
Dynamic: classifier
Dynamic: description
Dynamic: description-content-type
Dynamic: home-page
Dynamic: license
Dynamic: license-file
Dynamic: requires-dist
Dynamic: requires-python
Dynamic: summary
